LICENSE
README.md
setup.py
stable_ts.egg-info/PKG-INFO
stable_ts.egg-info/SOURCES.txt
stable_ts.egg-info/dependency_links.txt
stable_ts.egg-info/entry_points.txt
stable_ts.egg-info/requires.txt
stable_ts.egg-info/top_level.txt
stable_whisper/__init__.py
stable_whisper/__main__.py
stable_whisper/_version.py
stable_whisper/alignment.py
stable_whisper/decode.py
stable_whisper/default.py
stable_whisper/options.py
stable_whisper/quantization.py
stable_whisper/result.py
stable_whisper/text_output.py
stable_whisper/timing.py
stable_whisper/utils.py
stable_whisper/video_output.py
stable_whisper/whisper_compatibility.py
stable_whisper/audio/__init__.py
stable_whisper/audio/demucs.py
stable_whisper/audio/dfnet.py
stable_whisper/audio/noisereduce.py
stable_whisper/audio/output.py
stable_whisper/audio/utils.py
stable_whisper/non_whisper/__init__.py
stable_whisper/non_whisper/alignment.py
stable_whisper/non_whisper/refinement.py
stable_whisper/non_whisper/transcribe.py
stable_whisper/stabilization/__init__.py
stable_whisper/stabilization/nonvad.py
stable_whisper/stabilization/silero_vad.py
stable_whisper/stabilization/utils.py
stable_whisper/whisper_word_level/__init__.py
stable_whisper/whisper_word_level/cli.py
stable_whisper/whisper_word_level/faster_whisper.py
stable_whisper/whisper_word_level/hf_whisper.py
stable_whisper/whisper_word_level/original_whisper.py
test/test_align.py
test/test_locate.py
test/test_refine.py
test/test_transcribe.py